pyrandomset/__init__.py
pyrandomset-0.1.2.dist-info/LICENSE
pyrandomset-0.1.2.dist-info/METADATA
pyrandomset-0.1.2.dist-info/WHEEL
pyrandomset-0.1.2.dist-info/top_level.txt
pyrandomset-0.1.2.dist-info/RECORD
