Metadata-Version: 2.1
Name: pyrandomset
Version: 0.1.2
Summary: Generate random characters based on character set.
Home-page: https://github.com/nokcode/pyrandomset
Author: Rafael Ribeiro
License: UNKNOWN
Platform: UNKNOWN
Classifier: Programming Language :: Python :: 3.6
Classifier: License :: OSI Approved :: MIT License
Classifier: Operating System :: OS Independent
Requires-Python: >=3.6
